README.md
setup.cfg
setup.py
native/checks.d
native/checks_data.d
native/pyterato_native.d
pyterato/__init__.py
pyterato/cli.py
pyterato/version.py
pyterato/worditerator_base.py
pyterato/worditerator_lo.py
pyterato/worditerator_txtfile.py
pyterato.egg-info/PKG-INFO
pyterato.egg-info/SOURCES.txt
pyterato.egg-info/dependency_links.txt
pyterato.egg-info/entry_points.txt
pyterato.egg-info/top_level.txt