Metadata-Version: 1.1
Name: pyterato
Version: 0.6.0
Summary: Python application to lint Spanish literary language from LibreOffice
Home-page: https://github.com/juanjux/pyterato
Author: Juanjo Alvarez Martinez
Author-email: juanjo@juanjoalvarez.net
License: GPL 3
Download-URL: https://github.com/juanjux/pyterato/archive/0.6.0.tar.gz
Platform: UNKNOWN
Classifier: Development Status :: 3 - Alpha
Classifier: Environment :: Console
Classifier: Intended Audience :: Other Audience
Classifier: Topic :: Office/Business
Classifier: Operating System :: OS Independent
Classifier: Programming Language :: Python :: 3
Classifier: Programming Language :: Python :: 3.6
